{
  "W": 13,
  "H": 13,
  "m": [
    [
      1,
      1,
      1,
      1,
      1,
      1,
      1,
      1,
      1,
      1,
      1,
      1,
      1
    ],
    [
      1,
      0,
      0,
      0,
      0,
      0,
      0,
      0,
      0,
      0,
      0,
      0,
      1
    ],
    [
      1,
      1,
      1,
      1,
      1,
      0,
      0,
      0,
      1,
      1,
      1,
      1,
      1
    ],
    [
      1,
      0,
      209,
      0,
      1,
      1,
      1,
      1,
      1,
      0,
      0,
      0,
      1
    ],
    [
      1,
      0,
      210,
      0,
      85,
      1,
      211,
      1,
      85,
      0,
      0,
      0,
      1
    ],
    [
      1,
      1,
      1,
      1,
      1,
      1,
      0,
      1,
      1,
      1,
      1,
      1,
      1
    ],
    [
      1,
      209,
      28,
      209,
      1,
      1,
      0,
      1,
      1,
      209,
      27,
      209,
      1
    ],
    [
      1,
      0,
      210,
      0,
      1,
      1,
      0,
      1,
      1,
      0,
      210,
      0,
      1
    ],
    [
      1,
      0,
      0,
      0,
      1,
      1,
      0,
      1,
      1,
      0,
      0,
      0,
      1
    ],
    [
      1,
      81,
      1,
      81,
      1,
      1,
      83,
      1,
      1,
      81,
      1,
      81,
      1
    ],
    [
      1,
      0,
      1,
      0,
      1,
      0,
      0,
      0,
      1,
      0,
      1,
      0,
      1
    ],
    [
      1,
      88,
      1,
      0,
      217,
      0,
      87,
      0,
      217,
      0,
      1,
      32,
      1
    ],
    [
      1,
      1,
      1,
      1,
      1,
      1,
      1,
      1,
      1,
      1,
      1,
      1,
      1
    ]
  ],
  "bl": [
    {
      "x": 2,
      "y": 3,
      "id": "skeleton",
      "cls": "enemys"
    },
    {
      "x": 2,
      "y": 4,
      "id": "skeletonSoldier",
      "cls": "enemys"
    },
    {
      "x": 4,
      "y": 4,
      "id": "specialDoor",
      "cls": "animates"
    },
    {
      "x": 6,
      "y": 4,
      "id": "skeletonCaptain",
      "cls": "enemys"
    },
    {
      "x": 8,
      "y": 4,
      "id": "specialDoor",
      "cls": "animates"
    },
    {
      "x": 1,
      "y": 6,
      "id": "skeleton",
      "cls": "enemys"
    },
    {
      "x": 2,
      "y": 6,
      "id": "blueGem",
      "cls": "items"
    },
    {
      "x": 3,
      "y": 6,
      "id": "skeleton",
      "cls": "enemys"
    },
    {
      "x": 9,
      "y": 6,
      "id": "skeleton",
      "cls": "enemys"
    },
    {
      "x": 10,
      "y": 6,
      "id": "redGem",
      "cls": "items"
    },
    {
      "x": 11,
      "y": 6,
      "id": "skeleton",
      "cls": "enemys"
    },
    {
      "x": 2,
      "y": 7,
      "id": "skeletonSoldier",
      "cls": "enemys"
    },
    {
      "x": 10,
      "y": 7,
      "id": "skeletonSoldier",
      "cls": "enemys"
    },
    {
      "x": 1,
      "y": 9,
      "id": "yellowDoor",
      "cls": "animates"
    },
    {
      "x": 3,
      "y": 9,
      "id": "yellowDoor",
      "cls": "animates"
    },
    {
      "x": 6,
      "y": 9,
      "id": "redDoor",
      "cls": "animates"
    },
    {
      "x": 9,
      "y": 9,
      "id": "yellowDoor",
      "cls": "animates"
    },
    {
      "x": 11,
      "y": 9,
      "id": "yellowDoor",
      "cls": "animates"
    },
    {
      "x": 1,
      "y": 11,
      "id": "downFloor",
      "cls": "terrains"
    },
    {
      "x": 4,
      "y": 11,
      "id": "bluePriest",
      "cls": "enemys"
    },
    {
      "x": 6,
      "y": 11,
      "id": "upFloor",
      "cls": "terrains"
    },
    {
      "x": 8,
      "y": 11,
      "id": "bluePriest",
      "cls": "enemys"
    },
    {
      "x": 11,
      "y": 11,
      "id": "bluePotion",
      "cls": "items"
    }
  ]
}